integration/__init__.py
tests/gridmapping/__init__.py
tests/gridmapping/test_assertions.py
tests/gridmapping/test_base.py
tests/gridmapping/test_bboxes.py
tests/gridmapping/test_cfconv.py
tests/gridmapping/test_coords.py
tests/gridmapping/test_dataset.py
tests/gridmapping/test_helpers.py
tests/gridmapping/test_regular.py
tests/gridmapping/test_transform.py
xcube_resampling/__init__.py
xcube_resampling/affine.py
xcube_resampling/coarsen.py
xcube_resampling/constants.py
xcube_resampling/dask.py
xcube_resampling/rectify.py
xcube_resampling/reproject.py
xcube_resampling/spatial.py
xcube_resampling/temporal.py
xcube_resampling/utils.py
xcube_resampling/version.py
xcube_resampling/gridmapping/__init__.py
xcube_resampling/gridmapping/assertions.py
xcube_resampling/gridmapping/base.py
xcube_resampling/gridmapping/bboxes.py
xcube_resampling/gridmapping/cfconv.py
xcube_resampling/gridmapping/coords.py
xcube_resampling/gridmapping/dataset.py
xcube_resampling/gridmapping/helpers.py
xcube_resampling/gridmapping/regular.py
xcube_resampling/gridmapping/transform.py
xcube_resampling/gridmapping/undefined.py
xcube_resampling-0.2.4.dist-info/licenses/LICENSE
xcube_resampling-0.2.4.dist-info/METADATA
xcube_resampling-0.2.4.dist-info/WHEEL
xcube_resampling-0.2.4.dist-info/top_level.txt
xcube_resampling-0.2.4.dist-info/RECORD
