Metadata-Version: 2.4
Name: xcube-resampling
Version: 0.2.4
Summary: A package to resample, reproject, and rectify geospatial datasets.
Author: xcube Development Team
License: MIT
Project-URL: Documentation, https://github.com/xcube-dev/xcube-resampling
Project-URL: Repository, https://github.com/xcube-dev/xcube-resampling
Project-URL: Changelog, https://github.com/xcube-dev/xcube-resampling/blob/main/CHANGES.md
Project-URL: Issues, https://github.com/xcube-dev/xcube-resampling/issues
Keywords: xcube,xarray,dask,reprojection,rectification,affine transformation,parallel processing
Classifier: Development Status :: 5 - Production/Stable
Classifier: Intended Audience :: Science/Research
Classifier: Intended Audience :: Developers
Classifier: License :: OSI Approved :: Apache Software License
Classifier: Programming Language :: Python :: 3
Classifier: Programming Language :: Python :: 3.10
Classifier: Programming Language :: Python :: 3.11
Classifier: Programming Language :: Python :: 3.12
Classifier: Programming Language :: Python :: 3.13
Classifier: Topic :: Software Development
Classifier: Topic :: Scientific/Engineering
Classifier: Typing :: Typed
Classifier: Operating System :: Microsoft :: Windows
Classifier: Operating System :: POSIX
Classifier: Operating System :: Unix
Classifier: Operating System :: MacOS
Requires-Python: >=3.10
License-File: LICENSE
Requires-Dist: affine>=2.2
Requires-Dist: dask>=2021.6
Requires-Dist: dask-image>=0.6
Requires-Dist: numba>=0.52
Requires-Dist: numpy>=1.16
Requires-Dist: pyproj>=3.0
Requires-Dist: xarray>=2024.7
Requires-Dist: zarr<3,>=2.11
Provides-Extra: dev
Requires-Dist: build; extra == "dev"
Requires-Dist: hatch; extra == "dev"
Requires-Dist: twine; extra == "dev"
Requires-Dist: black; extra == "dev"
Requires-Dist: isort; extra == "dev"
Requires-Dist: ruff; extra == "dev"
Requires-Dist: pytest; extra == "dev"
Requires-Dist: pytest-cov; extra == "dev"
Requires-Dist: jupyterlab; extra == "dev"
Requires-Dist: matplotlib; extra == "dev"
Provides-Extra: doc
Requires-Dist: mkdocs; extra == "doc"
Requires-Dist: mkdocs-autorefs; extra == "doc"
Requires-Dist: mkdocs-material; extra == "doc"
Requires-Dist: mkdocs-jupyter; extra == "doc"
Requires-Dist: mkdocstrings; extra == "doc"
Requires-Dist: mkdocstrings-python; extra == "doc"
Dynamic: license-file
